recordsearch_data_scraper/__init__.py
recordsearch_data_scraper/_modidx.py
recordsearch_data_scraper/_nbdev.py
recordsearch_data_scraper/scrapers.py
recordsearch_data_scraper-0.1.0.dist-info/LICENSE
recordsearch_data_scraper-0.1.0.dist-info/METADATA
recordsearch_data_scraper-0.1.0.dist-info/WHEEL
recordsearch_data_scraper-0.1.0.dist-info/entry_points.txt
recordsearch_data_scraper-0.1.0.dist-info/top_level.txt
recordsearch_data_scraper-0.1.0.dist-info/RECORD
