Metadata-Version: 2.1
Name: recordsearch-data-scraper
Version: 0.1.0
Summary: Tool for extracting machine-readable data from the National Archives of Australia online database, Recordsearch.
Home-page: https://github.com/wragge/recordsearch_data_scraper
Author: Tim Sherratt
Author-email: tim@timsherratt.org
License: MIT License
Keywords: nbdev jupyter notebook python
Platform: UNKNOWN
Classifier: Development Status :: 4 - Beta
Classifier: Intended Audience :: Developers
Classifier: Natural Language :: English
Classifier: Programming Language :: Python :: 3.8
Classifier: Programming Language :: Python :: 3.9
Classifier: Programming Language :: Python :: 3.10
Classifier: License :: OSI Approved :: MIT License
Requires-Python: >=3.8
Requires-Dist: mechanicalsoup
Requires-Dist: sqlitedict
Requires-Dist: arrow
Provides-Extra: dev
Requires-Dist: jupyterlab ; extra == 'dev'
Requires-Dist: nbdev ; extra == 'dev'
Requires-Dist: jupyterlab-code-formatter ; extra == 'dev'
Requires-Dist: black ; extra == 'dev'
Requires-Dist: isort ; extra == 'dev'
